[
    {
        "title":"几分钟才算'快枪手'，想打持久战该怎么做",
        "class":"两性",
        "time":"今天",
        "image":"https://news.91160.com/uploads/allimg/180424/24-1P4241406140-L.jpg",
        "url":"https://wap.91160.com/news/liangxing/16080.html"
    },
    {
        "title":"看东西模糊、视力下降？不一定是近视这么简单！ ",
        "class":"养生",
        "time":"今天",
        "image":"https://news.91160.com/uploads/allimg/180424/24-1P4241343100-L.jpg",
        "url":"https://wap.91160.com/news/yangsheng/16078.html"
    },
    {
        "title":"吃不对也会近视？这些近视原因80%的人都不知道！",
        "class":"养生",
        "time":"昨天",
        "image":"https://news.91160.com/uploads/allimg/180423/24-1P4231042220-L.jpg",
        "url":"https://wap.91160.com/news/liangxing/16003.html"
    },
    {
        "title":"这些病都是憋尿憋出来的！看完你还敢再憋吗？",
        "class":"两性",
        "time":"昨天",
        "image":"https://news.91160.com/uploads/allimg/180423/24_042309351a629.gif",
        "url":"https://wap.91160.com/news/liangxing/16002.html"
    },
    {
        "title":"心情多差才算抑郁症？知道这个真相你肯定吓一跳 ",
        "class":"医生说",
        "time":"04/19",
        "image":"https://news.91160.com/uploads/allimg/180419/24_041Z93335CM.gif",
        "url":"https://wap.91160.com/news/yishengshuo/15862.html"
    }
]

